heraldopy/__init__.py
heraldopy/chromedriver_updater.py
heraldopy/ocr.py
heraldopy/onedrive_helper.py
heraldopy/utils.py
heraldopy-1.0.16.dist-info/licenses/LICENSE
heraldopy-1.0.16.dist-info/METADATA
heraldopy-1.0.16.dist-info/WHEEL
heraldopy-1.0.16.dist-info/top_level.txt
heraldopy-1.0.16.dist-info/RECORD
