Metadata-Version: 2.4
Name: heraldopy
Version: 1.0.16
Summary: A set of automation tools
Home-page: https://github.com/yourusername/heraldopy
Author: Heraldo Almeida
Author-email: heraldo.almeida@gmail.com
License: MIT
Classifier: Programming Language :: Python :: 3
Classifier: License :: OSI Approved :: MIT License
Classifier: Operating System :: OS Independent
Requires-Python: >=3.6
License-File: LICENSE
Requires-Dist: requests
Requires-Dist: msal
Requires-Dist: wget
Requires-Dist: numpy
Requires-Dist: pandas
Requires-Dist: tk
Requires-Dist: rapidfuzz
Dynamic: author
Dynamic: author-email
Dynamic: classifier
Dynamic: description
Dynamic: description-content-type
Dynamic: home-page
Dynamic: license
Dynamic: license-file
Dynamic: requires-dist
Dynamic: requires-python
Dynamic: summary
